cci_os_worker/README.md
cci_os_worker/__init__.py
cci_os_worker/all_facets.py
cci_os_worker/deleter.py
cci_os_worker/directory.py
cci_os_worker/errors.py
cci_os_worker/filehandlers/__init__.py
cci_os_worker/filehandlers/generic_file.py
cci_os_worker/filehandlers/geojson.py
cci_os_worker/filehandlers/netcdf_file.py
cci_os_worker/filehandlers/util.py
cci_os_worker/path_tools.py
cci_os_worker/tests/__init__.py
cci_os_worker/tests/test_consistency.py
cci_os_worker/utils.py
cci_os_worker-0.8.1.dist-info/LICENSE
cci_os_worker-0.8.1.dist-info/METADATA
cci_os_worker-0.8.1.dist-info/WHEEL
cci_os_worker-0.8.1.dist-info/entry_points.txt
cci_os_worker-0.8.1.dist-info/RECORD
