Metadata-Version: 2.3
Name: cci-os-worker
Version: 0.8.1
Summary: Worker repo to execute the steps for CCI Opensearch Ingestion, namely facet and tag scanning and updates to the CEDA FBI
License: BSD 3 - See License file
Author: Daniel Westwood
Author-email: daniel.westwood@stfc.ac.uk
Requires-Python: >=3.9,<4
Classifier: Intended Audience :: Developers
Classifier: License :: OSI Approved :: BSD License
Classifier: Operating System :: OS Independent
Classifier: Programming Language :: Python
Classifier: Programming Language :: Python :: 3.8
Requires-Dist: aiofiles (>=24.1.0,<25.0.0)
Requires-Dist: cci-facet-scanner (>=0.7.0,<1)
Requires-Dist: cci-tag-scanner (>=2.6.0,<3)
Requires-Dist: elasticsearch (>=8,<9)
Requires-Dist: ldap3 (>=2.9,<3.0)
Requires-Dist: python-dateutil (>=2.9.0.post0,<3.0.0)
Requires-Dist: python-magic (>=0.4.22,<0.5.0)
Requires-Dist: pyyaml (>=6.0.2,<7.0.0)
Requires-Dist: slack-sdk (>=3.35.0,<4.0.0)
